{
  "operationConfig" : {
    "name" : "deleterentokil7057",
    "type" : "MappedToBackend",
    "cachable" : false,
    "smsEnabled" : false,
    "security" : "authorized_app_user",
    "responseEncoding" : "UTF-8",
    "httpMethod" : "GET",
    "decodeResponseBody" : false,
    "referencingEndpoint" : "default",
    "inputs" : [ {
      "id" : "id",
      "scope" : "request",
      "dataType" : "number",
      "encode" : true,
      "passNull" : false,
      "isExtended" : false
    } ],
    "odata" : [ {
      "id" : "$filter",
      "dataType" : "string",
      "encode" : true,
      "accessType" : "readonly",
      "isExtended" : false
    } ],
    "applyCommonMapping" : true,
    "applyRequestCommonMapping" : true,
    "applyResponseCommonMapping" : true,
    "entityMetadata" : "{\"entityAttributeTypeList\":[{\"name\":\"id\",\"jdbcType\":4,\"columnTypeName\":\"INT\",\"columnDecimalDigits\":0,\"autoGenerated\":true,\"creatable\":false,\"updatable\":false,\"primary\":true,\"softDelete\":false,\"lastModified\":false},{\"name\":\"service\",\"jdbcType\":12,\"columnTypeName\":\"VARCHAR\",\"columnDecimalDigits\":0,\"autoGenerated\":false,\"creatable\":true,\"updatable\":true,\"primary\":false,\"softDelete\":false,\"lastModified\":false},{\"name\":\"type\",\"jdbcType\":12,\"columnTypeName\":\"VARCHAR\",\"columnDecimalDigits\":0,\"autoGenerated\":false,\"creatable\":true,\"updatable\":true,\"primary\":false,\"softDelete\":false,\"lastModified\":false},{\"name\":\"date\",\"jdbcType\":91,\"columnTypeName\":\"DATE\",\"columnDecimalDigits\":0,\"autoGenerated\":false,\"creatable\":true,\"updatable\":true,\"primary\":false,\"softDelete\":false,\"lastModified\":false},{\"name\":\"name\",\"jdbcType\":12,\"columnTypeName\":\"VARCHAR\",\"columnDecimalDigits\":0,\"autoGenerated\":false,\"creatable\":true,\"updatable\":true,\"primary\":false,\"softDelete\":false,\"lastModified\":false},{\"name\":\"address\",\"jdbcType\":12,\"columnTypeName\":\"VARCHAR\",\"columnDecimalDigits\":0,\"autoGenerated\":false,\"creatable\":true,\"updatable\":true,\"primary\":false,\"softDelete\":false,\"lastModified\":false}],\"relationshipTypeList\":[],\"name\":\"rentokil\",\"schemaName\":\"railway\",\"entityType\":\"com.kony.rdbms.metadata.model.AnnotatedTable\"}",
    "opcode" : "delete",
    "backendMeta" : {
      "qualifiedObjectName" : "railway.rentokil",
      "backendObjectName" : "rentokil"
    },
    "relationshipHierarchyMapping" : {
      "children" : [ ],
      "name" : "rentokil",
      "actions" : {
        "delete" : true
      },
      "selected" : true
    },
    "requestXmlMappingOverride" : false,
    "responseXmlMappingOverride" : false,
    "mapperData" : [ {
      "name" : "base mapper1",
      "order" : 1,
      "requestXmlMappingOverride" : false,
      "responseXmlMappingOverride" : false,
      "disabled" : false,
      "applyCommonMapping" : true,
      "applyRequestCommonMapping" : true,
      "applyResponseCommonMapping" : true
    } ]
  },
  "enableFrontendUrl" : false,
  "customVerb" : false
}