{
  "android": {
    "font_name": "default",
    "font_size": 71,
    "isForked": false
  },
  "androidwearos": {
    "font_name": "default",
    "font_size": 107,
    "isForked": false
  },
  "background_color": "ffffffff",
  "bg_type": "one",
  "border_color": "666666ff",
  "border_radius": 2,
  "border_style": "custom",
  "border_type": 0,
  "border_width": 1,
  "desktopweb": {
    "bottom_left_border_color": "666666ff",
    "bottom_left_border_radius": 2,
    "bottom_left_border_style": "rc",
    "bottom_left_border_width": 1,
    "bottom_right_border_color": "666666ff",
    "bottom_right_border_radius": 2,
    "bottom_right_border_style": "rc",
    "bottom_right_border_width": 1,
    "customCSS": "width: 100%; \npadding: 11px 14px; \nborder: 1px solid #e0e0e0; \nborder-radius: 6px; \nfont-size: 14px; \ncolor: #333; \nbackground: #fafafa; \noutline: none; \nfont-family: 'Segoe UI', sans-serif;",
    "font_name": "Helvetica",
    "font_size": 188,
    "isCustomCSSEnabled": true,
    "isForked": true,
    "top_left_border_color": "666666ff",
    "top_left_border_radius": 2,
    "top_left_border_style": "rc",
    "top_left_border_width": 1,
    "top_right_border_color": "666666ff",
    "top_right_border_radius": 2,
    "top_right_border_style": "rc",
    "top_right_border_width": 1
  },
  "fontSizeInPx": true,
  "font_color": "00000099",
  "font_name": "iphoneSystem",
  "font_size": 188,
  "font_style": "italic",
  "font_weight": "400",
  "ipad": {
    "font_name": "System",
    "font_size": 107,
    "isForked": false
  },
  "iphone": {
    "font_name": "System",
    "font_size": 75,
    "isForked": false
  },
  "isDefaultSkin": false,
  "kiosk": {
    "font_name": "Helvetica",
    "font_size": 188,
    "isForked": false
  },
  "kuid": "se2062de49c841e9bce10005e22a60dd",
  "nativemac": {
    "bottom_left_border_color": "666666ff",
    "bottom_left_border_radius": 2,
    "bottom_left_border_style": "rc",
    "bottom_left_border_width": 1,
    "bottom_right_border_color": "666666ff",
    "bottom_right_border_radius": 2,
    "bottom_right_border_style": "rc",
    "bottom_right_border_width": 1,
    "customCSS": "width: 100%; \npadding: 11px 14px; \nborder: 1px solid #e0e0e0; \nborder-radius: 6px; \nfont-size: 14px; \ncolor: #333; \nbackground: #fafafa; \noutline: none; \nfont-family: 'Segoe UI', sans-serif;",
    "font_name": "Helvetica",
    "font_size": 188,
    "isCustomCSSEnabled": true,
    "isForked": true,
    "top_left_border_color": "666666ff",
    "top_left_border_radius": 2,
    "top_left_border_style": "rc",
    "top_left_border_width": 1,
    "top_right_border_color": "666666ff",
    "top_right_border_radius": 2,
    "top_right_border_style": "rc",
    "top_right_border_width": 1
  },
  "nativewin": {
    "bottom_left_border_color": "666666ff",
    "bottom_left_border_radius": 2,
    "bottom_left_border_style": "rc",
    "bottom_left_border_width": 1,
    "bottom_right_border_color": "666666ff",
    "bottom_right_border_radius": 2,
    "bottom_right_border_style": "rc",
    "bottom_right_border_width": 1,
    "customCSS": "width: 100%; \npadding: 11px 14px; \nborder: 1px solid #e0e0e0; \nborder-radius: 6px; \nfont-size: 14px; \ncolor: #333; \nbackground: #fafafa; \noutline: none; \nfont-family: 'Segoe UI', sans-serif;",
    "font_name": "Helvetica",
    "font_size": 188,
    "isCustomCSSEnabled": true,
    "isForked": true,
    "top_left_border_color": "666666ff",
    "top_left_border_radius": 2,
    "top_left_border_style": "rc",
    "top_left_border_width": 1,
    "top_right_border_color": "666666ff",
    "top_right_border_radius": 2,
    "top_right_border_style": "rc",
    "top_right_border_width": 1
  },
  "spaan": {
    "bottom_left_border_color": "666666ff",
    "bottom_left_border_radius": 2,
    "bottom_left_border_style": "rc",
    "bottom_left_border_width": 1,
    "bottom_right_border_color": "666666ff",
    "bottom_right_border_radius": 2,
    "bottom_right_border_style": "rc",
    "bottom_right_border_width": 1,
    "customCSS": "width: 100%; \npadding: 11px 14px; \nborder: 1px solid #e0e0e0; \nborder-radius: 6px; \nfont-size: 14px; \ncolor: #333; \nbackground: #fafafa; \noutline: none; \nfont-family: 'Segoe UI', sans-serif;",
    "font_name": "Helvetica",
    "font_size": 200,
    "isCustomCSSEnabled": true,
    "isForked": true,
    "top_left_border_color": "666666ff",
    "top_left_border_radius": 2,
    "top_left_border_style": "rc",
    "top_left_border_width": 1,
    "top_right_border_color": "666666ff",
    "top_right_border_radius": 2,
    "top_right_border_style": "rc",
    "top_right_border_width": 1
  },
  "spaandroidtablet": {
    "bottom_left_border_color": "666666ff",
    "bottom_left_border_radius": 2,
    "bottom_left_border_style": "rc",
    "bottom_left_border_width": 1,
    "bottom_right_border_color": "666666ff",
    "bottom_right_border_radius": 2,
    "bottom_right_border_style": "rc",
    "bottom_right_border_width": 1,
    "customCSS": "width: 100%; \npadding: 11px 14px; \nborder: 1px solid #e0e0e0; \nborder-radius: 6px; \nfont-size: 14px; \ncolor: #333; \nbackground: #fafafa; \noutline: none; \nfont-family: 'Segoe UI', sans-serif;",
    "font_name": "Helvetica",
    "font_size": 167,
    "isCustomCSSEnabled": true,
    "isForked": true,
    "top_left_border_color": "666666ff",
    "top_left_border_radius": 2,
    "top_left_border_style": "rc",
    "top_left_border_width": 1,
    "top_right_border_color": "666666ff",
    "top_right_border_radius": 2,
    "top_right_border_style": "rc",
    "top_right_border_width": 1
  },
  "spaip": {
    "bottom_left_border_color": "666666ff",
    "bottom_left_border_radius": 2,
    "bottom_left_border_style": "rc",
    "bottom_left_border_width": 1,
    "bottom_right_border_color": "666666ff",
    "bottom_right_border_radius": 2,
    "bottom_right_border_style": "rc",
    "bottom_right_border_width": 1,
    "customCSS": "width: 100%; \npadding: 11px 14px; \nborder: 1px solid #e0e0e0; \nborder-radius: 6px; \nfont-size: 14px; \ncolor: #333; \nbackground: #fafafa; \noutline: none; \nfont-family: 'Segoe UI', sans-serif;",
    "font_name": "Helvetica",
    "font_size": 205,
    "isCustomCSSEnabled": true,
    "isForked": true,
    "top_left_border_color": "666666ff",
    "top_left_border_radius": 2,
    "top_left_border_style": "rc",
    "top_left_border_width": 1,
    "top_right_border_color": "666666ff",
    "top_right_border_radius": 2,
    "top_right_border_style": "rc",
    "top_right_border_width": 1
  },
  "spaipad": {
    "bottom_left_border_color": "666666ff",
    "bottom_left_border_radius": 2,
    "bottom_left_border_style": "rc",
    "bottom_left_border_width": 1,
    "bottom_right_border_color": "666666ff",
    "bottom_right_border_radius": 2,
    "bottom_right_border_style": "rc",
    "bottom_right_border_width": 1,
    "customCSS": "width: 100%; \npadding: 11px 14px; \nborder: 1px solid #e0e0e0; \nborder-radius: 6px; \nfont-size: 14px; \ncolor: #333; \nbackground: #fafafa; \noutline: none; \nfont-family: 'Segoe UI', sans-serif;",
    "font_name": "Helvetica",
    "font_size": 176,
    "isCustomCSSEnabled": true,
    "isForked": true,
    "top_left_border_color": "666666ff",
    "top_left_border_radius": 2,
    "top_left_border_style": "rc",
    "top_left_border_width": 1,
    "top_right_border_color": "666666ff",
    "top_right_border_radius": 2,
    "top_right_border_style": "rc",
    "top_right_border_width": 1
  },
  "spawindowstablet": {
    "bottom_left_border_color": "666666ff",
    "bottom_left_border_radius": 2,
    "bottom_left_border_style": "rc",
    "bottom_left_border_width": 1,
    "bottom_right_border_color": "666666ff",
    "bottom_right_border_radius": 2,
    "bottom_right_border_style": "rc",
    "bottom_right_border_width": 1,
    "customCSS": "width: 100%; \npadding: 11px 14px; \nborder: 1px solid #e0e0e0; \nborder-radius: 6px; \nfont-size: 14px; \ncolor: #333; \nbackground: #fafafa; \noutline: none; \nfont-family: 'Segoe UI', sans-serif;",
    "font_name": "Helvetica",
    "font_size": 176,
    "isCustomCSSEnabled": true,
    "isForked": true,
    "top_left_border_color": "666666ff",
    "top_left_border_radius": 2,
    "top_left_border_style": "rc",
    "top_left_border_width": 1,
    "top_right_border_color": "666666ff",
    "top_right_border_radius": 2,
    "top_right_border_style": "rc",
    "top_right_border_width": 1
  },
  "spawinphone8": {
    "bottom_left_border_color": "666666ff",
    "bottom_left_border_radius": 2,
    "bottom_left_border_style": "rc",
    "bottom_left_border_width": 1,
    "bottom_right_border_color": "666666ff",
    "bottom_right_border_radius": 2,
    "bottom_right_border_style": "rc",
    "bottom_right_border_width": 1,
    "customCSS": "width: 100%; \npadding: 11px 14px; \nborder: 1px solid #e0e0e0; \nborder-radius: 6px; \nfont-size: 14px; \ncolor: #333; \nbackground: #fafafa; \noutline: none; \nfont-family: 'Segoe UI', sans-serif;",
    "font_name": "Helvetica",
    "font_size": 250,
    "isCustomCSSEnabled": true,
    "isForked": true,
    "top_left_border_color": "666666ff",
    "top_left_border_radius": 2,
    "top_left_border_style": "rc",
    "top_left_border_width": 1,
    "top_right_border_color": "666666ff",
    "top_right_border_radius": 2,
    "top_right_border_style": "rc",
    "top_right_border_width": 1
  },
  "tabrcandroid": {
    "font_name": "default",
    "font_size": 178,
    "isForked": false
  },
  "wType": "TextField",
  "watchos": {
    "font_name": "System",
    "font_size": 107,
    "isForked": false
  },
  "windows8": {
    "font_name": "None",
    "font_size": 73,
    "isForked": false
  },
  "winphone8": {
    "font_name": "None",
    "font_size": 100,
    "isForked": false
  }
}